AUTHOR
LICENSE
MANIFEST.in
README.rst
setup.cfg
setup.py
doc/source/_static/pyconnectomist.png
doc/source/_static/carousel/altas3.png
doc/source/_static/carousel/atlas2.png
doc/source/_static/carousel/atlas4.png
pyConnectomist.egg-info/PKG-INFO
pyConnectomist.egg-info/SOURCES.txt
pyConnectomist.egg-info/dependency_links.txt
pyConnectomist.egg-info/requires.txt
pyConnectomist.egg-info/top_level.txt
pyconnectomist/__init__.py
pyconnectomist/exceptions.py
pyconnectomist/info.py
pyconnectomist/manufacturers.py
pyconnectomist/wrappers.py
pyconnectomist/clustering/__init__.py
pyconnectomist/clustering/labeling.py
pyconnectomist/preproc/__init__.py
pyconnectomist/preproc/all_steps.py
pyconnectomist/preproc/eddy.py
pyconnectomist/preproc/mask.py
pyconnectomist/preproc/outliers.py
pyconnectomist/preproc/qc.py
pyconnectomist/preproc/qspace.py
pyconnectomist/preproc/registration.py
pyconnectomist/preproc/susceptibility.py
pyconnectomist/scripts/pyconnectomist_dtifit
pyconnectomist/scripts/pyconnectomist_preproc
pyconnectomist/scripts/pyconnectomist_tractography
pyconnectomist/tests/test_wrappers.py
pyconnectomist/tests/tests_clustering/test_labeling.py
pyconnectomist/tests/tests_preproc/test_all_steps.py
pyconnectomist/tests/tests_preproc/test_eddy.py
pyconnectomist/tests/tests_preproc/test_mask.py
pyconnectomist/tests/tests_preproc/test_outliers.py
pyconnectomist/tests/tests_preproc/test_qc.py
pyconnectomist/tests/tests_preproc/test_qspace.py
pyconnectomist/tests/tests_preproc/test_registration.py
pyconnectomist/tests/tests_preproc/test_susceptibility.py
pyconnectomist/tests/tests_tractography/test_all_steps.py
pyconnectomist/tests/tests_tractography/test_mask.py
pyconnectomist/tests/tests_tractography/test_model.py
pyconnectomist/tests/tests_tractography/test_tractography.py
pyconnectomist/tests/tests_utils/test_dwitools.py
pyconnectomist/tests/tests_utils/test_filetools.py
pyconnectomist/tests/tests_utils/test_pdftools.py
pyconnectomist/tractography/__init__.py
pyconnectomist/tractography/all_steps.py
pyconnectomist/tractography/mask.py
pyconnectomist/tractography/model.py
pyconnectomist/tractography/tractography.py
pyconnectomist/utils/__init__.py
