Metadata-Version: 2.1
Name: pyConnectomist
Version: 2.0.0
Summary: 
